pyinterboleto/__init__.py
pyinterboleto/auth.py
pyinterboleto/baixa.py
pyinterboleto/boleto.py
pyinterboleto/common/__init__.py
pyinterboleto/common/desconto.py
pyinterboleto/common/mora.py
pyinterboleto/common/multa.py
pyinterboleto/common/tipo_pessoa.py
pyinterboleto/consulta/__init__.py
pyinterboleto/consulta/detalhado.py
pyinterboleto/consulta/lista.py
pyinterboleto/consulta/pdf.py
pyinterboleto/emissao/__init__.py
pyinterboleto/emissao/beneficiario.py
pyinterboleto/emissao/emissor.py
pyinterboleto/emissao/mensagem.py
pyinterboleto/emissao/pagador.py
pyinterboleto/exceptions.py
pyinterboleto/utils/__init__.py
pyinterboleto/utils/floats.py
pyinterboleto/utils/requests.py
pyinterboleto/utils/sanitize.py
pyinterboleto/utils/url.py
pyinterboleto-1.0.3.dist-info/METADATA
pyinterboleto-1.0.3.dist-info/LICENSE
pyinterboleto-1.0.3.dist-info/WHEEL
pyinterboleto-1.0.3.dist-info/RECORD
