Metadata-Version: 2.1
Name: pyinterboleto
Version: 1.0.3
Summary: Biblioteca para facilitar o manuseio de boletos de contas PJ no Banco Inter.
Home-page: https://github.com/feslima/pyinterboleto
License: LGPL-3.0
Author: Felipe Souza Lima
Author-email: feslima93@gmail.com
Requires-Python: >=3.8,<4.0
Classifier: License :: OSI Approved :: GNU Lesser General Public License v3 (LGPLv3)
Classifier: Operating System :: OS Independent
Classifier: Programming Language :: Python :: 3
Classifier: Programming Language :: Python :: 3.8
Classifier: Programming Language :: Python :: 3.9
Classifier: Programming Language :: Python :: 3.10
Classifier: Programming Language :: Python :: 3.11
Requires-Dist: Unidecode (>=1.2.0,<2.0.0)
Requires-Dist: dacite (>=1.6.0,<2.0.0)
Requires-Dist: requests (>=2.26.0,<3.0.0)
Requires-Dist: tabulate (>=0.8.9,<0.9.0)
Project-URL: Bug Tracker, https://github.com/feslima/pyinterboleto/issues
Project-URL: Repository, https://github.com/feslima/pyinterboleto
